[
	{
		"toUrl": "/selllikehotcakes1",
		"imgUrl": "https://img.sanfu.com/img/goods/list/201706081406168600.jpg",
		"imgUrli": "http://img.sanfu.com/img/index_new/summary.png",
		"digital":"￥62.1",
		"Cross":"31",
		"Cross2":"￥69.0",
		"text":"三福2017夏装新品圆领男印花T恤 休闲短袖亚麻上衣男372251"
	}, {
		"toUrl": "/selllikehotcakes2",
		"imgUrl": "https://img.sanfu.com/img/goods/list/201701131709125113.jpg",
		"imgUrli": "http://img.sanfu.com/img/index_new/summary.png",
		"digital":"￥26.1",
		"Cross":"89",
		"Cross2":"￥29.0",
		"text":"三福2017夏装新品圆领男印花T恤 休闲短袖亚麻上衣男372251"
	}, {
		"toUrl": "/selllikehotcakes3",
		"imgUrl": "https://img.sanfu.com/img/goods/list/201706291731525219.jpg",
		"imgUrli": "http://img.sanfu.com/img/index_new/summary.png",
		"digital":"￥62.1",
		"Cross":"85",
		"Cross2":"￥69.0",
		"text":"三福2017夏装新品圆领男印花T恤 休闲短袖亚麻上衣男372251"
	},
	{
		"toUrl": "/selllikehotcakes4",
		"imgUrl": "https://img.sanfu.com/img/goods/list/201706161050559135.jpg",
		"imgUrli": "http://img.sanfu.com/img/index_new/summary.png",
		"digital":"￥62.1",
		"Cross":"108",
		"Cross2":"￥69.0",
		"text":"三福2017夏装新品圆领男印花T恤 休闲短袖亚麻上衣男372251"
	}, {
		"toUrl": "/selllikehotcakes5",
		"imgUrl": "https://img.sanfu.com/img/goods/list/201705241439469990.jpg",
		"imgUrli": "http://img.sanfu.com/img/index_new/summary.png",
		"digital":"￥53.1",
		"Cross":"130",
		"Cross2":"￥59.0",
		"text":"三福2017夏装新品圆领男印花T恤 休闲短袖亚麻上衣男372251"
	}, {
		"toUrl": "/selllikehotcakes6",
		"imgUrl": "https://img.sanfu.com/img/goods/list/201704121733072188.jpg",
		"imgUrli": "http://img.sanfu.com/img/index_new/summary.png",
		"digital":"￥107.1",
		"Cross":"74",
		"Cross2":"￥119.0",
		"text":"三福2017夏装新品圆领男印花T恤 休闲短袖亚麻上衣男372251"
	}
]
