[
	{
		"toUrl": "/Details",
		"imgUrl": "https://img.sanfu.com/img/news/201706031729487359.jpg",
		"class":"rem rem1"
	}, {
		"toUrl": "/Details2",
		"imgUrl": "https://img.sanfu.com/img/news/201706031729438074.jpg",
		"class":"rem rem2"
	}, {
		"toUrl": "/Details3",
		"imgUrl": "https://img.sanfu.com/img/news/201706031729396353.jpg",
		"class":"rem rem3"
	},
	{
		"toUrl": "/Details4",
		"imgUrl": "https://img.sanfu.com/img/news/201706031729351636.jpg",
		"class":"rem rem4"
	}, {
		"toUrl": "/Details5",
		"imgUrl": "https://img.sanfu.com/img/news/201706031729273378.jpg",
		"class":"rem rem5"
	}, {
		"toUrl": "/Details6",
		"imgUrl": "https://img.sanfu.com/img/news/201706031729193541.jpg",
		"class":"rem rem6"
	},
	{
		"toUrl": "/Details7",
		"imgUrl": "https://img.sanfu.com/img/news/201706031729114597.jpg",
		"class":"/Details rem7"
	}, {
		"toUrl": "/Details8",
		"imgUrl": "https://img.sanfu.com/img/news/201706031728599086.jpg",
		"class":"rem rem6"
	},
	{
		"toUrl": "/Details9",
		"imgUrl": "https://img.sanfu.com/img/news/201706031728518542.jpg",
		"class":"/Details rem7"
	}
]
